phtuankiet/__init__.py
phtuankiet-0.0.1.dist-info/METADATA
phtuankiet-0.0.1.dist-info/WHEEL
phtuankiet-0.0.1.dist-info/RECORD
