Metadata-Version: 2.4
Name: phtuankiet
Version: 0.0.1
Summary: anh iu tất cả các em
Project-URL: Homepage, https://github.com/phtuankiet/phtuankiet
Project-URL: Issues, https://github.com/phtuankiet/phtuankiet/issues
Author-email: Phan Tuan Kiet <phtuankiet.dev@gmail.com>
Classifier: License :: OSI Approved :: MIT License
Classifier: Operating System :: OS Independent
Classifier: Programming Language :: Python :: 3
Requires-Python: >=3.7
Requires-Dist: requests
